gems/__init__.py
gems/datatypes.py
gems/decorators.py
gems/metaclasses.py
gems-0.4.0.dist-info/LICENSE
gems-0.4.0.dist-info/METADATA
gems-0.4.0.dist-info/WHEEL
gems-0.4.0.dist-info/top_level.txt
gems-0.4.0.dist-info/RECORD
