Metadata-Version: 1.1
Name: gems
Version: 0.4.0
Summary: Python utilities for data manipulation and management.
Home-page: https://github.com/bprinty/gems
Author: Blake Printy
Author-email: bprinty@gmail.com
License: Apache-2.0
Keywords: gems,data,structures,types,filesystem,management
Platform: UNKNOWN
Classifier: Intended Audience :: Developers
Classifier: License :: OSI Approved :: Apple Public Source License
Classifier: Natural Language :: English
Classifier: Programming Language :: Python :: 2
Classifier: Programming Language :: Python :: 2.6
Classifier: Programming Language :: Python :: 2.7
Classifier: Programming Language :: Python :: 3
Classifier: Programming Language :: Python :: 3.3
Classifier: Programming Language :: Python :: 3.4
